omoide_cache/__init__.py
omoide_cache/cache.py
omoide_cache/cache_decorator.py
omoide_cache/examples/__init__.py
omoide_cache/examples/example_1.py
omoide_cache/examples/example_2.py
omoide_cache/examples/example_3.py
omoide_cache/examples/example_4.py
omoide_cache/examples/example_active_users/__init__.py
omoide_cache/examples/example_active_users/main.py
omoide_cache/examples/example_active_users/user.py
omoide_cache/examples/example_active_users/user_service.py
omoide_cache/examples/example_calculation/__init__.py
omoide_cache/examples/example_calculation/main.py
omoide_cache/examples/example_nlp_spacy/__init__.py
omoide_cache/examples/example_nlp_spacy/main.py
omoide_cache/examples/example_nlp_spacy/spacy_service.py
omoide_cache/tests/__init__.py
omoide_cache/tests/test_decorator.py
omoide_cache/tests/test_decorator_multiple.py
omoide_cache/tests/test_expire_computed.py
omoide_cache/tests/test_expire_size.py
omoide_cache/tests/test_refresh_independent.py
tutorials/__init__.py
tutorials/tutorial_fastapi/__init__.py
tutorials/tutorial_fastapi/main.py
tutorials/tutorial_fastapi/resources/__init__.py
tutorials/tutorial_fastapi/resources/resource_ping.py
tutorials/tutorial_fastapi/services/__init__.py
tutorials/tutorial_fastapi/services/service_books.py
tutorials/tutorial_introduction/__init__.py
tutorials/tutorial_introduction/main_basic.py
tutorials/tutorial_introduction/main_expire_computed.py
tutorials/tutorial_introduction/main_refresh_independent.py
omoide_cache-0.1.3.dist-info/LICENSE.txt
omoide_cache-0.1.3.dist-info/METADATA
omoide_cache-0.1.3.dist-info/WHEEL
omoide_cache-0.1.3.dist-info/top_level.txt
omoide_cache-0.1.3.dist-info/RECORD
