Metadata-Version: 2.1
Name: omoide-cache
Version: 0.1.3
Summary: Robust, highly tunable and easy-to-integrate in-memory cache solution written in pure Python, with no dependencies.
Home-page: https://github.com/jpleorx/omoide-cache
Author: Leo Ertuna
Author-email: leo.ertuna@gmail.com
License: Creative Commons Attribution-NonCommercial-NoDerivatives 4.0 International Public License
Download-URL: https://pypi.org/project/omoide-cache/
Keywords: cache,decorator,annotation,in-memory
Platform: UNKNOWN
